docs2prompt/__init__.py
docs2prompt/api.py
docs2prompt/github.py
docs2prompt/main.py
docs2prompt/utils.py
docs2prompt/web_docs.py
docs2prompt-0.3.0.dist-info/METADATA
docs2prompt-0.3.0.dist-info/WHEEL
docs2prompt-0.3.0.dist-info/entry_points.txt
docs2prompt-0.3.0.dist-info/top_level.txt
docs2prompt-0.3.0.dist-info/RECORD
