Metadata-Version: 2.2
Name: docs2prompt
Version: 0.3.0
Summary: Convert software documentation to prompt for LLMs
Project-URL: Homepage, https://github.com/rezabrizi/docs2prompt
Requires-Python: >=3.12
Requires-Dist: beautifulsoup4>=4.13.3
Requires-Dist: click>=8.1.8
Requires-Dist: html2text>=2024.2.26
Requires-Dist: requests<3.0.0,>=2.32.3
Requires-Dist: setuptools>=76.0.0
